{"cameraMode":{"drawMode":0,"name":"Shaded","section":"Shading Mode"},"sceneLighting":true,"audioPlay":false,"sceneViewState":{"m_AlwaysRefresh":false,"showFog":true,"showSkybox":false,"showFlares":true,"showImageEffects":true,"showParticleSystems":true,"showVisualEffectGraphs":true,"m_FxEnabled":true},"in2DMode":false,"pivot":{"x":-32.9599494934082,"y":-13.448774337768555,"z":18.220718383789064},"rotation":{"x":-0.16780926287174226,"y":0.5034542083740234,"z":-0.10038536041975022,"w":-0.8416112065315247},"size":23.393314361572267,"orthographic":false}